{
    "Content": [{
        "IOTSceneId": "540971eb-14d9-49d9-8d58-073eb44d0774",
        "HardWareDeviceKey": 9,
        "IOTSceneBind": {
            "IOTSceneThresholds": [{
                "HardWareDeviceKey": 9,
                "MinValue": -0.1000,
                "MaxValue": 0.9000,
                "DefaultDelayedValue": 0,
                "DefaultOpenValue": 0.00,
                "DefaultOpenValueOperate": 1,
                "DefaultMinDuration": 0,
                "DefaultMinComplete": 0,
                "DeviceUnit": "%LEL",
                "DeviceUnitDesc": "默认阈值(可燃气体浓度)",
                "DeviceNumberType": 1,
                "DeviceNumberPrecision": "0.0",
                "DeviceNormalValue": 0
            }],
            "IOTSceneWorkTimes": [{
                "StartTime": "00:00:00",
                "EndTime": "23:59:59"
            }]
        },
        "IOTClassifyNum": 1,
        "IOTDeviceTypeId": "841198b9-42c3-4b0e-abce-dc9e81e078db",
        "IOTSceneName": "可燃气体浓度传感器",
        "IOTSceneMonitorName": "浓度专检",
        "IOTSceneLegalRule": "123",
        "IOTSceneWarningContent": "测试123{MaxValue}{MaxValue}",
        "DeviceModels": null,
        "PersonWarningSets": null,
        "PersonWarningContent": null
    }, {
        "IOTSceneId": "3251d2ee-e32e-42b8-ae22-45920e11d9be",
        "HardWareDeviceKey": 8,
        "IOTSceneBind": {
            "IOTSceneThresholds": [{
                "HardWareDeviceKey": 6,
                "MinValue": 0.0000,
                "MaxValue": 0.0000,
                "DefaultDelayedValue": 0,
                "DefaultOpenValue": 0.00,
                "DefaultOpenValueOperate": 1,
                "DefaultMinDuration": 0,
                "DefaultMinComplete": 0,
                "DeviceUnit": "℃",
                "DeviceUnitDesc": "默认阈值(温度)",
                "DeviceNumberType": 1,
                "DeviceNumberPrecision": "0.0",
                "DeviceNormalValue": 0
            }, {
                "HardWareDeviceKey": 7,
                "MinValue": 0.1000,
                "MaxValue": 0.5000,
                "DefaultDelayedValue": 0,
                "DefaultOpenValue": 0.00,
                "DefaultOpenValueOperate": 1,
                "DefaultMinDuration": 0,
                "DefaultMinComplete": 0,
                "DeviceUnit": "%",
                "DeviceUnitDesc": "默认阈值(湿度)",
                "DeviceNumberType": 1,
                "DeviceNumberPrecision": "0.0",
                "DeviceNormalValue": 0
            }],
            "IOTSceneWorkTimes": [{
                "StartTime": "00:00:00",
                "EndTime": "23:59:59"
            }]
        },
        "IOTClassifyNum": 1,
        "IOTDeviceTypeId": "5f7c8f60-3bf0-4704-a2fd-b1a20b0f6f9e",
        "IOTSceneName": "温湿度传感器",
        "IOTSceneMonitorName": "湿度检测",
        "IOTSceneLegalRule": "123",
        "IOTSceneWarningContent": "{DeviceUnit}{DefaultOpenValueOperate}|{DefaultOpenValueOperate}",
        "DeviceModels": null,
        "PersonWarningSets": null,
        "PersonWarningContent": null
    }, {
        "IOTSceneId": "d097a719-9614-47a6-9148-f5e6bacecc8a",
        "HardWareDeviceKey": 8,
        "IOTSceneBind": {
            "IOTSceneThresholds": [{
                "HardWareDeviceKey": 6,
                "MinValue": 0.0000,
                "MaxValue": 0.0000,
                "DefaultDelayedValue": 0,
                "DefaultOpenValue": 0.00,
                "DefaultOpenValueOperate": 1,
                "DefaultMinDuration": 0,
                "DefaultMinComplete": 0,
                "DeviceUnit": "℃",
                "DeviceUnitDesc": "温度A",
                "DeviceNumberType": 1,
                "DeviceNumberPrecision": "0.0",
                "DeviceNormalValue": 0
            }, {
                "HardWareDeviceKey": 7,
                "MinValue": 0.0000,
                "MaxValue": 0.0000,
                "DefaultDelayedValue": 0,
                "DefaultOpenValue": 0.00,
                "DefaultOpenValueOperate": 1,
                "DefaultMinDuration": 0,
                "DefaultMinComplete": 0,
                "DeviceUnit": "%",
                "DeviceUnitDesc": "湿度A",
                "DeviceNumberType": 1,
                "DeviceNumberPrecision": "0.0",
                "DeviceNormalValue": 0
            }],
            "IOTSceneWorkTimes": [{
                "StartTime": "00:00:00",
                "EndTime": "23:59:59"
            }]
        },
        "IOTClassifyNum": 1,
        "IOTDeviceTypeId": "b4be3676-fd6f-4663-8194-e4ca9caf3685",
        "IOTSceneName": "储藏间",
        "IOTSceneMonitorName": "温度监测1",
        "IOTSceneLegalRule": "134",
        "IOTSceneWarningContent": "#湿度A#{MinValue}{MaxValue}{DeviceUnit}|#湿度A#{NowDateTime}",
        "DeviceModels": null,
        "PersonWarningSets": null,
        "PersonWarningContent": null
    }, {
        "IOTSceneId": "06f5382b-7e8f-44ad-bbd7-cf82b62e706e",
        "HardWareDeviceKey": 32,
        "IOTSceneBind": {
            "IOTSceneThresholds": [{
                "HardWareDeviceKey": 32,
                "MinValue": 0.0000,
                "MaxValue": 0.0000,
                "DefaultDelayedValue": 0,
                "DefaultOpenValue": 0.00,
                "DefaultOpenValueOperate": 1,
                "DefaultMinDuration": 0,
                "DefaultMinComplete": 0,
                "DeviceUnit": "ppm",
                "DeviceUnitDesc": "默认阈值(氨气浓度)",
                "DeviceNumberType": 1,
                "DeviceNumberPrecision": "0.0",
                "DeviceNormalValue": 0
            }],
            "IOTSceneWorkTimes": [{
                "StartTime": "00:00:00",
                "EndTime": "23:59:59"
            }]
        },
        "IOTClassifyNum": 1,
        "IOTDeviceTypeId": "d34b05cc-0ed8-463f-8141-659a04536446",
        "IOTSceneName": "氨气浓度测试1",
        "IOTSceneMonitorName": "浓度监测",
        "IOTSceneLegalRule": "气体",
        "IOTSceneWarningContent": "#默认阈值(氨气浓度)#{DefaultOpenValue}{DefaultOpenValueOperate}",
        "DeviceModels": null,
        "PersonWarningSets": null,
        "PersonWarningContent": null
    }, {
        "IOTSceneId": "808ab126-9caa-4eda-887b-065a32655651",
        "HardWareDeviceKey": 17,
        "IOTSceneBind": {
            "IOTSceneThresholds": [{
                "HardWareDeviceKey": 17,
                "MinValue": 0.0000,
                "MaxValue": 0.0000,
                "DefaultDelayedValue": 0,
                "DefaultOpenValue": 0.00,
                "DefaultOpenValueOperate": 1,
                "DefaultMinDuration": 0,
                "DefaultMinComplete": 0,
                "DeviceUnit": "",
                "DeviceUnitDesc": "烟雾报警",
                "DeviceNumberType": 2,
                "DeviceNumberPrecision": "",
                "DeviceNormalValue": 0
            }],
            "IOTSceneWorkTimes": [{
                "StartTime": "00:00:00",
                "EndTime": "23:59:59"
            }]
        },
        "IOTClassifyNum": 1,
        "IOTDeviceTypeId": "140d5fb3-722f-4a78-83b9-9bc4892c17ed",
        "IOTSceneName": "厨房烟雾传感器",
        "IOTSceneMonitorName": "烟雾监测",
        "IOTSceneLegalRule": "食品安全法要求烟雾浓度在正常范围",
        "IOTSceneWarningContent": "#烟雾报警#{StoreName}",
        "DeviceModels": null,
        "PersonWarningSets": null,
        "PersonWarningContent": null
    }, {
        "IOTSceneId": "040de2c6-b0eb-4a78-893c-3dd29aa7ecab",
        "HardWareDeviceKey": 8,
        "IOTSceneBind": {
            "IOTSceneThresholds": [{
                "HardWareDeviceKey": 6,
                "MinValue": 0.0000,
                "MaxValue": 0.0000,
                "DefaultDelayedValue": 0,
                "DefaultOpenValue": 0.00,
                "DefaultOpenValueOperate": 1,
                "DefaultMinDuration": 0,
                "DefaultMinComplete": 0,
                "DeviceUnit": "℃",
                "DeviceUnitDesc": "温度A",
                "DeviceNumberType": 1,
                "DeviceNumberPrecision": "0.0",
                "DeviceNormalValue": 0
            }, {
                "HardWareDeviceKey": 7,
                "MinValue": 0.0000,
                "MaxValue": 0.0000,
                "DefaultDelayedValue": 0,
                "DefaultOpenValue": 0.00,
                "DefaultOpenValueOperate": 1,
                "DefaultMinDuration": 0,
                "DefaultMinComplete": 0,
                "DeviceUnit": "%",
                "DeviceUnitDesc": "湿度A",
                "DeviceNumberType": 1,
                "DeviceNumberPrecision": "0.0",
                "DeviceNormalValue": 0
            }],
            "IOTSceneWorkTimes": [{
                "StartTime": "00:00:00",
                "EndTime": "23:59:59"
            }]
        },
        "IOTClassifyNum": 1,
        "IOTDeviceTypeId": "b4be3676-fd6f-4663-8194-e4ca9caf3685",
        "IOTSceneName": "厨房温湿度传感器",
        "IOTSceneMonitorName": "JH-xGQ-BX-GX1",
        "IOTSceneLegalRule": "食品药品安全条例",
        "IOTSceneWarningContent": "#温度A#{NowDate}{NowDateTime}|#湿度A#{NowDateTime}{NowValue}",
        "DeviceModels": null,
        "PersonWarningSets": null,
        "PersonWarningContent": null
    }, {
        "IOTSceneId": "aea908f9-6289-43c0-bceb-173122f39aef",
        "HardWareDeviceKey": 6,
        "IOTSceneBind": {
            "IOTSceneThresholds": [{
                "HardWareDeviceKey": 6,
                "MinValue": 0.0000,
                "MaxValue": 0.0000,
                "DefaultDelayedValue": 0,
                "DefaultOpenValue": 0.00,
                "DefaultOpenValueOperate": 1,
                "DefaultMinDuration": 0,
                "DefaultMinComplete": 0,
                "DeviceUnit": "℃",
                "DeviceUnitDesc": "默认阈值(温度)",
                "DeviceNumberType": 1,
                "DeviceNumberPrecision": "0.0",
                "DeviceNormalValue": 0
            }],
            "IOTSceneWorkTimes": [{
                "StartTime": "00:00:00",
                "EndTime": "23:59:59"
            }]
        },
        "IOTClassifyNum": 1,
        "IOTDeviceTypeId": "1e837bd8-985e-4945-8925-8dd287328499",
        "IOTSceneName": "储藏室温度传感器",
        "IOTSceneMonitorName": "储藏室温度检测1",
        "IOTSceneLegalRule": "温度法规",
        "IOTSceneWarningContent": "#默认阈值(温度)#{NowDateTime}",
        "DeviceModels": null,
        "PersonWarningSets": null,
        "PersonWarningContent": null
    }, {
        "IOTSceneId": "1a1d9a02-677f-4880-b9be-45882c1b1602",
        "HardWareDeviceKey": 8,
        "IOTSceneBind": {
            "IOTSceneThresholds": [{
                "HardWareDeviceKey": 6,
                "MinValue": 10.0000,
                "MaxValue": 15.0000,
                "DefaultDelayedValue": 0,
                "DefaultOpenValue": 0.00,
                "DefaultOpenValueOperate": 1,
                "DefaultMinDuration": 0,
                "DefaultMinComplete": 0,
                "DeviceUnit": "℃",
                "DeviceUnitDesc": "温度A",
                "DeviceNumberType": 1,
                "DeviceNumberPrecision": "0.0",
                "DeviceNormalValue": 0
            }, {
                "HardWareDeviceKey": 7,
                "MinValue": 0.0000,
                "MaxValue": 5.0000,
                "DefaultDelayedValue": 0,
                "DefaultOpenValue": 0.00,
                "DefaultOpenValueOperate": 1,
                "DefaultMinDuration": 0,
                "DefaultMinComplete": 0,
                "DeviceUnit": "%",
                "DeviceUnitDesc": "湿度A",
                "DeviceNumberType": 1,
                "DeviceNumberPrecision": "0.0",
                "DeviceNormalValue": 0
            }],
            "IOTSceneWorkTimes": [{
                "StartTime": "00:00:00",
                "EndTime": "23:59:59"
            }]
        },
        "IOTClassifyNum": 1,
        "IOTDeviceTypeId": "b4be3676-fd6f-4663-8194-e4ca9caf3685",
        "IOTSceneName": "药店阴凉处温湿度传感器A",
        "IOTSceneMonitorName": "药店阴凉处温湿度监测A",
        "IOTSceneLegalRule": "测试法律法规",
        "IOTSceneWarningContent": "药店阴凉区温湿度出现异常，当前温度：{NowValue}，当前湿度：{NowValue}，请立即处理！|药店阴凉区温湿度出现异常，当前温度：{NowValue}，当前湿度：{NowValue}，请立即处理！",
        "DeviceModels": null,
        "PersonWarningSets": null,
        "PersonWarningContent": null
    }, {
        "IOTSceneId": "2184c22d-3de6-4c63-80b7-302961298b7f",
        "HardWareDeviceKey": 11,
        "IOTSceneBind": {
            "IOTSceneThresholds": [{
                "HardWareDeviceKey": 11,
                "MinValue": 0.0000,
                "MaxValue": 0.0000,
                "DefaultDelayedValue": 0,
                "DefaultOpenValue": 0.20,
                "DefaultOpenValueOperate": 1,
                "DefaultMinDuration": 20,
                "DefaultMinComplete": 1,
                "DeviceUnit": "uW/cm2",
                "DeviceUnitDesc": "默认开启值(紫外线强度)",
                "DeviceNumberType": 1,
                "DeviceNumberPrecision": "0.0",
                "DeviceNormalValue": 0
            }],
            "IOTSceneWorkTimes": [{
                "StartTime": "00:00:00",
                "EndTime": "23:59:59"
            }]
        },
        "IOTClassifyNum": 3,
        "IOTDeviceTypeId": "b6d79dee-adfe-4a11-a4c4-bb1fe779b978",
        "IOTSceneName": "专间紫外线传感器",
        "IOTSceneMonitorName": "专间紫外线消毒任务监测",
        "IOTSceneLegalRule": "食品安全法要求每日需对专间空气进行消毒",
        "IOTSceneWarningContent": "专间今日还未进行紫外线消毒，请立即处理！",
        "DeviceModels": null,
        "PersonWarningSets": null,
        "PersonWarningContent": null
    }, {
        "IOTSceneId": "09359420-43c7-44a6-9847-10d359c37baa",
        "HardWareDeviceKey": 6,
        "IOTSceneBind": {
            "IOTSceneThresholds": [{
                "HardWareDeviceKey": 6,
                "MinValue": 0.0000,
                "MaxValue": 0.0000,
                "DefaultDelayedValue": 0,
                "DefaultOpenValue": 0.00,
                "DefaultOpenValueOperate": 1,
                "DefaultMinDuration": 0,
                "DefaultMinComplete": 0,
                "DeviceUnit": "℃",
                "DeviceUnitDesc": "默认阈值(温度)",
                "DeviceNumberType": 1,
                "DeviceNumberPrecision": "0.0",
                "DeviceNormalValue": 0
            }],
            "IOTSceneWorkTimes": [{
                "StartTime": "00:00:00",
                "EndTime": "23:59:59"
            }]
        },
        "IOTClassifyNum": 1,
        "IOTDeviceTypeId": "1e837bd8-985e-4945-8925-8dd287328499",
        "IOTSceneName": "1",
        "IOTSceneMonitorName": "1",
        "IOTSceneLegalRule": "1",
        "IOTSceneWarningContent": "1",
        "DeviceModels": null,
        "PersonWarningSets": null,
        "PersonWarningContent": null
    }, {
        "IOTSceneId": "9d656471-6b37-4290-8f41-f4a3bede492e",
        "HardWareDeviceKey": 6,
        "IOTSceneBind": {
            "IOTSceneThresholds": [{
                "HardWareDeviceKey": 6,
                "MinValue": 0.0000,
                "MaxValue": 0.0000,
                "DefaultDelayedValue": 0,
                "DefaultOpenValue": 60.00,
                "DefaultOpenValueOperate": 1,
                "DefaultMinDuration": 20,
                "DefaultMinComplete": 1,
                "DeviceUnit": "℃",
                "DeviceUnitDesc": "默认开启值(温度)",
                "DeviceNumberType": 1,
                "DeviceNumberPrecision": "0.0",
                "DeviceNormalValue": 0
            }],
            "IOTSceneWorkTimes": [{
                "StartTime": "00:00:00",
                "EndTime": "23:59:59"
            }]
        },
        "IOTClassifyNum": 3,
        "IOTDeviceTypeId": "9ba6f518-b5d1-4e66-8917-c4d7d814fde1",
        "IOTSceneName": "消毒柜温度传感器",
        "IOTSceneMonitorName": "消毒柜高温消毒任务监测",
        "IOTSceneLegalRule": "食品生产法要求每日需对设施设备进行消毒",
        "IOTSceneWarningContent": "消毒柜今日还未进行高温消毒，请立即处理！",
        "DeviceModels": null,
        "PersonWarningSets": null,
        "PersonWarningContent": null
    }, {
        "IOTSceneId": "c0c9b3ea-6fb1-4766-89ca-c64d94b163ad",
        "HardWareDeviceKey": 35,
        "IOTSceneBind": {
            "IOTSceneThresholds": [{
                "HardWareDeviceKey": 35,
                "MinValue": 0.0000,
                "MaxValue": 0.0000,
                "DefaultDelayedValue": 0,
                "DefaultOpenValue": 0.00,
                "DefaultOpenValueOperate": 1,
                "DefaultMinDuration": 0,
                "DefaultMinComplete": 0,
                "DeviceUnit": "on/off",
                "DeviceUnitDesc": "可燃气体",
                "DeviceNumberType": 2,
                "DeviceNumberPrecision": "0",
                "DeviceNormalValue": 0
            }],
            "IOTSceneWorkTimes": [{
                "StartTime": "00:00:00",
                "EndTime": "23:59:59"
            }]
        },
        "IOTClassifyNum": 4,
        "IOTDeviceTypeId": "5bf2dbcf-fedc-4e55-a1e9-2f2ed4a371d8",
        "IOTSceneName": "民用可燃气体传感器",
        "IOTSceneMonitorName": "可燃气体-实时监测(民用)",
        "IOTSceneLegalRule": "食品安全法要求可燃气体浓度在正常范围",
        "IOTSceneWarningContent": "您好，市场监督管理局提醒您，您的门店{StoreName}，#默认阈值(可燃气体浓度)#可燃气体浓度超标，当前浓度：{NowValue}%LEL，请立即处理！",
        "DeviceModels": null,
        "PersonWarningSets": null,
        "PersonWarningContent": null
    }, {
        "IOTSceneId": "91ce1e3c-678d-455a-926c-75971372562a",
        "HardWareDeviceKey": 9,
        "IOTSceneBind": {
            "IOTSceneThresholds": [{
                "HardWareDeviceKey": 9,
                "MinValue": 0.0000,
                "MaxValue": 7.0000,
                "DefaultDelayedValue": 0,
                "DefaultOpenValue": 0.00,
                "DefaultOpenValueOperate": 1,
                "DefaultMinDuration": 0,
                "DefaultMinComplete": 0,
                "DeviceUnit": "%LEL",
                "DeviceUnitDesc": "默认阈值(可燃气体浓度)",
                "DeviceNumberType": 1,
                "DeviceNumberPrecision": "0.0",
                "DeviceNormalValue": 0
            }],
            "IOTSceneWorkTimes": [{
                "StartTime": "00:00:00",
                "EndTime": "23:59:59"
            }]
        },
        "IOTClassifyNum": 1,
        "IOTDeviceTypeId": "841198b9-42c3-4b0e-abce-dc9e81e078db",
        "IOTSceneName": "可燃气体传感器",
        "IOTSceneMonitorName": "可燃气体浓度实时监测(工业)",
        "IOTSceneLegalRule": "食品安全法要求可燃气体浓度在正常范围",
        "IOTSceneWarningContent": "您好，市场监督管理局提醒您，您的门店{StoreName}，#默认阈值(可燃气体浓度)#可燃气体浓度超标，当前浓度：{NowValue}%LEL，请立即处理！",
        "DeviceModels": null,
        "PersonWarningSets": null,
        "PersonWarningContent": null
    }, {
        "IOTSceneId": "b9c4656c-bf32-4c11-bc5f-705f1b577766",
        "HardWareDeviceKey": 6,
        "IOTSceneBind": {
            "IOTSceneThresholds": [{
                "HardWareDeviceKey": 7,
                "MinValue": 0.0000,
                "MaxValue": 250.0000,
                "DefaultDelayedValue": 0,
                "DefaultOpenValue": 0.00,
                "DefaultOpenValueOperate": 1,
                "DefaultMinDuration": 0,
                "DefaultMinComplete": 0,
                "DeviceUnit": "℃",
                "DeviceUnitDesc": "默认阈值(温度)",
                "DeviceNumberType": 1,
                "DeviceNumberPrecision": "0.0",
                "DeviceNormalValue": 0
            }],
            "IOTSceneWorkTimes": [{
                "StartTime": "00:00:00",
                "EndTime": "23:59:59"
            }]
        },
        "IOTClassifyNum": 1,
        "IOTDeviceTypeId": "1e837bd8-985e-4945-8925-8dd287328499",
        "IOTSceneName": "油锅温度传感器",
        "IOTSceneMonitorName": "油锅温度-实时监测",
        "IOTSceneLegalRule": "食品安全法要求油锅温度在正常范围",
        "IOTSceneWarningContent": "#默认阈值(温度)#油锅温度超标，当前温度：{NowValue}℃，请立即处理！",
        "DeviceModels": null,
        "PersonWarningSets": null,
        "PersonWarningContent": null
    }, {
        "IOTSceneId": "7752b0d8-f066-4bca-b249-a2f906a75b33",
        "HardWareDeviceKey": 13,
        "IOTSceneBind": {
            "IOTSceneThresholds": [{
                "HardWareDeviceKey": 13,
                "MinValue": 0.0000,
                "MaxValue": 0.0000,
                "DefaultDelayedValue": 10,
                "DefaultOpenValue": 0.00,
                "DefaultOpenValueOperate": 1,
                "DefaultMinDuration": 0,
                "DefaultMinComplete": 0,
                "DeviceUnit": "",
                "DeviceUnitDesc": "挡鼠板报警",
                "DeviceNumberType": 2,
                "DeviceNumberPrecision": "",
                "DeviceNormalValue": 0
            }],
            "IOTSceneWorkTimes": [{
                "StartTime": "00:00:00",
                "EndTime": "23:59:59"
            }]
        },
        "IOTClassifyNum": 2,
        "IOTDeviceTypeId": "1494c01b-7a9b-4acc-b7bd-68fec8062841",
        "IOTSceneName": "仓库挡鼠板位移传感器",
        "IOTSceneMonitorName": "仓库挡鼠板位移-实时监测",
        "IOTSceneLegalRule": "食品生产法要求仓库配置挡鼠板并不得长时间位移",
        "IOTSceneWarningContent": "仓库挡鼠板长时间位移，请立即处理！",
        "DeviceModels": null,
        "PersonWarningSets": null,
        "PersonWarningContent": null
    }, {
        "IOTSceneId": "66bc077d-b4ea-449a-b5c3-a4aca3f98897",
        "HardWareDeviceKey": 10,
        "IOTSceneBind": {
            "IOTSceneThresholds": [{
                "HardWareDeviceKey": 10,
                "MinValue": 0.0000,
                "MaxValue": 1.0000,
                "DefaultDelayedValue": 0,
                "DefaultOpenValue": 0.00,
                "DefaultOpenValueOperate": 1,
                "DefaultMinDuration": 0,
                "DefaultMinComplete": 0,
                "DeviceUnit": "mg/m3",
                "DeviceUnitDesc": "默认阈值(油烟浓度)",
                "DeviceNumberType": 1,
                "DeviceNumberPrecision": "0.0",
                "DeviceNormalValue": 0
            }],
            "IOTSceneWorkTimes": [{
                "StartTime": "00:00:00",
                "EndTime": "23:59:59"
            }]
        },
        "IOTClassifyNum": 1,
        "IOTDeviceTypeId": "9149fb11-9191-418f-8e59-fcd64d218070",
        "IOTSceneName": "油烟浓度传感器",
        "IOTSceneMonitorName": "油烟浓度-实时监测",
        "IOTSceneLegalRule": "食品安全法要求油烟浓度在正常范围",
        "IOTSceneWarningContent": "#默认阈值(油烟浓度)#油烟浓度超标，当前浓度：{NowValue}mg/m3，请立处理！",
        "DeviceModels": null,
        "PersonWarningSets": null,
        "PersonWarningContent": null
    }, {
        "IOTSceneId": "0979774d-dc65-40fb-b33a-1684dbf092ae",
        "HardWareDeviceKey": 32,
        "IOTSceneBind": {
            "IOTSceneThresholds": [{
                "HardWareDeviceKey": 32,
                "MinValue": 0.0000,
                "MaxValue": 0.2000,
                "DefaultDelayedValue": 0,
                "DefaultOpenValue": 0.00,
                "DefaultOpenValueOperate": 1,
                "DefaultMinDuration": 0,
                "DefaultMinComplete": 0,
                "DeviceUnit": "ppm",
                "DeviceUnitDesc": "默认阈值(氨气浓度)",
                "DeviceNumberType": 1,
                "DeviceNumberPrecision": "0.0",
                "DeviceNormalValue": 0
            }],
            "IOTSceneWorkTimes": [{
                "StartTime": "00:00:00",
                "EndTime": "23:59:59"
            }]
        },
        "IOTClassifyNum": 1,
        "IOTDeviceTypeId": "d34b05cc-0ed8-463f-8141-659a04536446",
        "IOTSceneName": "氨气浓度传感器",
        "IOTSceneMonitorName": "氨气浓度-实时监测",
        "IOTSceneLegalRule": "食品安全法要求洗手间氨气浓度在正常范围",
        "IOTSceneWarningContent": "#默认阈值(氨气浓度)#氨气浓度超标，当前浓度：{NowValue}ppm，请立即处理！",
        "DeviceModels": null,
        "PersonWarningSets": null,
        "PersonWarningContent": null
    }, {
        "IOTSceneId": "64d39c58-5523-4d99-8a98-6bccfdc4f7a4",
        "HardWareDeviceKey": 17,
        "IOTSceneBind": {
            "IOTSceneThresholds": [{
                "HardWareDeviceKey": 17,
                "MinValue": 0.0000,
                "MaxValue": 0.0000,
                "DefaultDelayedValue": 0,
                "DefaultOpenValue": 0.00,
                "DefaultOpenValueOperate": 1,
                "DefaultMinDuration": 0,
                "DefaultMinComplete": 0,
                "DeviceUnit": "",
                "DeviceUnitDesc": "烟雾报警",
                "DeviceNumberType": 2,
                "DeviceNumberPrecision": "",
                "DeviceNormalValue": 0
            }],
            "IOTSceneWorkTimes": [{
                "StartTime": "00:00:00",
                "EndTime": "23:59:59"
            }]
        },
        "IOTClassifyNum": 1,
        "IOTDeviceTypeId": "140d5fb3-722f-4a78-83b9-9bc4892c17ed",
        "IOTSceneName": "烟雾传感器",
        "IOTSceneMonitorName": "烟雾浓度-实时监测",
        "IOTSceneLegalRule": "食品安全法要求烟雾浓度在正常范围",
        "IOTSceneWarningContent": "烟雾浓度超标，请立即处理！",
        "DeviceModels": null,
        "PersonWarningSets": null,
        "PersonWarningContent": null
    }, {
        "IOTSceneId": "f94ab5e5-0af7-4101-b5bd-b46939a20483",
        "HardWareDeviceKey": 8,
        "IOTSceneBind": {
            "IOTSceneThresholds": [{
                "HardWareDeviceKey": 6,
                "MinValue": -20.0000,
                "MaxValue": 0.0000,
                "DefaultDelayedValue": 0,
                "DefaultOpenValue": 0.00,
                "DefaultOpenValueOperate": 1,
                "DefaultMinDuration": 0,
                "DefaultMinComplete": 0,
                "DeviceUnit": "℃",
                "DeviceUnitDesc": "默认阈值(温度)",
                "DeviceNumberType": 1,
                "DeviceNumberPrecision": "0.0",
                "DeviceNormalValue": 0
            }, {
                "HardWareDeviceKey": 7,
                "MinValue": 10.0000,
                "MaxValue": 75.0000,
                "DefaultDelayedValue": 0,
                "DefaultOpenValue": 0.00,
                "DefaultOpenValueOperate": 1,
                "DefaultMinDuration": 0,
                "DefaultMinComplete": 0,
                "DeviceUnit": "%",
                "DeviceUnitDesc": "默认阈值(湿度)",
                "DeviceNumberType": 1,
                "DeviceNumberPrecision": "0.0",
                "DeviceNormalValue": 0
            }],
            "IOTSceneWorkTimes": [{
                "StartTime": "00:00:00",
                "EndTime": "23:59:59"
            }]
        },
        "IOTClassifyNum": 1,
        "IOTDeviceTypeId": "5f7c8f60-3bf0-4704-a2fd-b1a20b0f6f9e",
        "IOTSceneName": "冰箱冷冻区温湿度传感器",
        "IOTSceneMonitorName": "冰箱冷冻区温湿度-实时监测",
        "IOTSceneLegalRule": "食品生产法要求冰箱冷冻区温湿度在正常范围",
        "IOTSceneWarningContent": "#默认阈值(湿度)#冰箱冷冻区温湿度出现异常，当前温度：{NowValue}，|#默认阈值(湿度)#冰箱冷冻区温湿度出现异常，当前温度：{NowValue}，",
        "DeviceModels": null,
        "PersonWarningSets": null,
        "PersonWarningContent": null
    }, {
        "IOTSceneId": "7c2b52f5-a0dc-4421-b45a-68ec0314ff7f",
        "HardWareDeviceKey": 8,
        "IOTSceneBind": {
            "IOTSceneThresholds": [{
                "HardWareDeviceKey": 7,
                "MinValue": 10.0000,
                "MaxValue": 75.0000,
                "DefaultDelayedValue": 0,
                "DefaultOpenValue": 0.00,
                "DefaultOpenValueOperate": 1,
                "DefaultMinDuration": 0,
                "DefaultMinComplete": 0,
                "DeviceUnit": "%",
                "DeviceUnitDesc": "默认阈值(湿度)",
                "DeviceNumberType": 1,
                "DeviceNumberPrecision": "0.0",
                "DeviceNormalValue": 0
            }, {
                "HardWareDeviceKey": 6,
                "MinValue": 0.0000,
                "MaxValue": 10.0000,
                "DefaultDelayedValue": 0,
                "DefaultOpenValue": 0.00,
                "DefaultOpenValueOperate": 1,
                "DefaultMinDuration": 0,
                "DefaultMinComplete": 0,
                "DeviceUnit": "℃",
                "DeviceUnitDesc": "默认阈值(温度)",
                "DeviceNumberType": 1,
                "DeviceNumberPrecision": "0.0",
                "DeviceNormalValue": 0
            }],
            "IOTSceneWorkTimes": [{
                "StartTime": "00:00:00",
                "EndTime": "23:59:59"
            }]
        },
        "IOTClassifyNum": 1,
        "IOTDeviceTypeId": "5f7c8f60-3bf0-4704-a2fd-b1a20b0f6f9e",
        "IOTSceneName": "冰箱冷藏区温湿度传感器",
        "IOTSceneMonitorName": "冰箱冷藏区温湿度-实时监测",
        "IOTSceneLegalRule": "食品生产法要求冰箱冷藏区温湿度在正常范围",
        "IOTSceneWarningContent": "#默认阈值(湿度)#冰箱冷藏区温湿度出现异常，当前温度：{NowValue}，|#默认阈值(湿度)#冰箱冷藏区温湿度出现异常，当前温度：{NowValue}，",
        "DeviceModels": null,
        "PersonWarningSets": null,
        "PersonWarningContent": null
    }, {
        "IOTSceneId": "3b56c158-5e06-4aef-ac2c-a17e264cbe0b",
        "HardWareDeviceKey": 8,
        "IOTSceneBind": {
            "IOTSceneThresholds": [{
                "HardWareDeviceKey": 6,
                "MinValue": 0.0000,
                "MaxValue": 10.0000,
                "DefaultDelayedValue": 0,
                "DefaultOpenValue": 0.00,
                "DefaultOpenValueOperate": 1,
                "DefaultMinDuration": 0,
                "DefaultMinComplete": 0,
                "DeviceUnit": "℃",
                "DeviceUnitDesc": "默认阈值(温度)",
                "DeviceNumberType": 1,
                "DeviceNumberPrecision": "0.0",
                "DeviceNormalValue": 0
            }, {
                "HardWareDeviceKey": 7,
                "MinValue": 35.0000,
                "MaxValue": 75.0000,
                "DefaultDelayedValue": 0,
                "DefaultOpenValue": 0.00,
                "DefaultOpenValueOperate": 1,
                "DefaultMinDuration": 0,
                "DefaultMinComplete": 0,
                "DeviceUnit": "%",
                "DeviceUnitDesc": "默认阈值(湿度)",
                "DeviceNumberType": 1,
                "DeviceNumberPrecision": "0.0",
                "DeviceNormalValue": 0
            }],
            "IOTSceneWorkTimes": [{
                "StartTime": "00:00:00",
                "EndTime": "23:59:59"
            }]
        },
        "IOTClassifyNum": 1,
        "IOTDeviceTypeId": "5f7c8f60-3bf0-4704-a2fd-b1a20b0f6f9e",
        "IOTSceneName": "留样冰箱温湿度传感器",
        "IOTSceneMonitorName": "留样冰箱温湿度-实时监测",
        "IOTSceneLegalRule": "食品安全法要求冰箱温湿度在正常范围",
        "IOTSceneWarningContent": "#默认阈值(温度)#留样冰箱温湿度出现异常，当前温度：{NowValue}℃，|#默认阈值(湿度)#当前湿度：{NowValue}%，请立即处理！",
        "DeviceModels": null,
        "PersonWarningSets": null,
        "PersonWarningContent": null
    }, {
        "IOTSceneId": "e51369a7-33d4-4d3b-8a7e-1730ed125dbd",
        "HardWareDeviceKey": 8,
        "IOTSceneBind": {
            "IOTSceneThresholds": [{
                "HardWareDeviceKey": 6,
                "MinValue": 0.0000,
                "MaxValue": 25.0000,
                "DefaultDelayedValue": 0,
                "DefaultOpenValue": 0.00,
                "DefaultOpenValueOperate": 1,
                "DefaultMinDuration": 0,
                "DefaultMinComplete": 0,
                "DeviceUnit": "℃",
                "DeviceUnitDesc": "默认阈值(温度)",
                "DeviceNumberType": 1,
                "DeviceNumberPrecision": "0.0",
                "DeviceNormalValue": 0
            }, {
                "HardWareDeviceKey": 7,
                "MinValue": 35.0000,
                "MaxValue": 75.0000,
                "DefaultDelayedValue": 0,
                "DefaultOpenValue": 0.00,
                "DefaultOpenValueOperate": 1,
                "DefaultMinDuration": 0,
                "DefaultMinComplete": 0,
                "DeviceUnit": "%",
                "DeviceUnitDesc": "默认阈值(湿度)",
                "DeviceNumberType": 1,
                "DeviceNumberPrecision": "0.0",
                "DeviceNormalValue": 0
            }],
            "IOTSceneWorkTimes": [{
                "StartTime": "00:00:00",
                "EndTime": "23:59:59"
            }]
        },
        "IOTClassifyNum": 1,
        "IOTDeviceTypeId": "5f7c8f60-3bf0-4704-a2fd-b1a20b0f6f9e",
        "IOTSceneName": "专间温湿度传感器",
        "IOTSceneMonitorName": "专间温湿度-实时监测",
        "IOTSceneLegalRule": "食品安全法要求专间温湿度在正常范围",
        "IOTSceneWarningContent": "#默认阈值(温度)#专间温湿度出现异常，当前温度：{NowValue}℃，|#默认阈值(湿度)#当前湿度：{NowValue}%，请立即处理！",
        "DeviceModels": null,
        "PersonWarningSets": null,
        "PersonWarningContent": null
    }, {
        "IOTSceneId": "d3347aaa-e5bd-4fa6-9d36-a97364c2c6ee",
        "HardWareDeviceKey": 8,
        "IOTSceneBind": {
            "IOTSceneThresholds": [{
                "HardWareDeviceKey": 7,
                "MinValue": 35.0000,
                "MaxValue": 75.0000,
                "DefaultDelayedValue": 0,
                "DefaultOpenValue": 0.00,
                "DefaultOpenValueOperate": 1,
                "DefaultMinDuration": 0,
                "DefaultMinComplete": 0,
                "DeviceUnit": "%",
                "DeviceUnitDesc": "默认阈值(湿度)",
                "DeviceNumberType": 1,
                "DeviceNumberPrecision": "0.0",
                "DeviceNormalValue": 0
            }, {
                "HardWareDeviceKey": 6,
                "MinValue": 0.0000,
                "MaxValue": 3.0000,
                "DefaultDelayedValue": 0,
                "DefaultOpenValue": 0.00,
                "DefaultOpenValueOperate": 1,
                "DefaultMinDuration": 0,
                "DefaultMinComplete": 0,
                "DeviceUnit": "℃",
                "DeviceUnitDesc": "默认阈值(温度)",
                "DeviceNumberType": 1,
                "DeviceNumberPrecision": "0.0",
                "DeviceNormalValue": 0
            }],
            "IOTSceneWorkTimes": [{
                "StartTime": "00:00:00",
                "EndTime": "23:59:59"
            }]
        },
        "IOTClassifyNum": 1,
        "IOTDeviceTypeId": "5f7c8f60-3bf0-4704-a2fd-b1a20b0f6f9e",
        "IOTSceneName": "食品生产冷藏间温湿度传感器",
        "IOTSceneMonitorName": "食品生产冷藏间温室-实时监测",
        "IOTSceneLegalRule": "食品生产法要求冷藏间温度在正常范围",
        "IOTSceneWarningContent": "#默认阈值(温度)#药店冷藏冰箱温湿度出现异常，当前温度：{NowValue}℃，|#默认阈值(湿度)#当前湿度：{NowValue}%，请立即处理！",
        "DeviceModels": null,
        "PersonWarningSets": null,
        "PersonWarningContent": null
    }, {
        "IOTSceneId": "c7718f9e-3c24-4fa5-a3b1-8677291c7896",
        "HardWareDeviceKey": 8,
        "IOTSceneBind": {
            "IOTSceneThresholds": [{
                "HardWareDeviceKey": 7,
                "MinValue": 35.0000,
                "MaxValue": 75.0000,
                "DefaultDelayedValue": 0,
                "DefaultOpenValue": 0.00,
                "DefaultOpenValueOperate": 1,
                "DefaultMinDuration": 0,
                "DefaultMinComplete": 0,
                "DeviceUnit": "%",
                "DeviceUnitDesc": "默认阈值(湿度)",
                "DeviceNumberType": 1,
                "DeviceNumberPrecision": "0.0",
                "DeviceNormalValue": 0
            }, {
                "HardWareDeviceKey": 6,
                "MinValue": 2.0000,
                "MaxValue": 8.0000,
                "DefaultDelayedValue": 0,
                "DefaultOpenValue": 0.00,
                "DefaultOpenValueOperate": 1,
                "DefaultMinDuration": 0,
                "DefaultMinComplete": 0,
                "DeviceUnit": "℃",
                "DeviceUnitDesc": "默认阈值(温度)",
                "DeviceNumberType": 1,
                "DeviceNumberPrecision": "0.0",
                "DeviceNormalValue": 0
            }],
            "IOTSceneWorkTimes": [{
                "StartTime": "00:00:00",
                "EndTime": "23:59:59"
            }]
        },
        "IOTClassifyNum": 1,
        "IOTDeviceTypeId": "5f7c8f60-3bf0-4704-a2fd-b1a20b0f6f9e",
        "IOTSceneName": "药店冷藏冰箱温湿度传感器",
        "IOTSceneMonitorName": "药店冷藏冰箱温湿度-实时监测",
        "IOTSceneLegalRule": "药品管理法要求冷藏柜温湿度在正常范围",
        "IOTSceneWarningContent": "#默认阈值(温度)#药店冷藏冰箱温湿度出现异常，当前温度：{NowValue}℃，|#默认阈值(湿度)#当前湿度：{NowValue}%，请立即处理！",
        "DeviceModels": null,
        "PersonWarningSets": null,
        "PersonWarningContent": null
    }, {
        "IOTSceneId": "10e5f726-9549-4855-91b6-139a61f14818",
        "HardWareDeviceKey": 8,
        "IOTSceneBind": {
            "IOTSceneThresholds": [{
                "HardWareDeviceKey": 7,
                "MinValue": 35.0000,
                "MaxValue": 75.0000,
                "DefaultDelayedValue": 0,
                "DefaultOpenValue": 0.00,
                "DefaultOpenValueOperate": 1,
                "DefaultMinDuration": 0,
                "DefaultMinComplete": 0,
                "DeviceUnit": "%",
                "DeviceUnitDesc": "默认阈值(湿度)",
                "DeviceNumberType": 1,
                "DeviceNumberPrecision": "0.0",
                "DeviceNormalValue": 0
            }, {
                "HardWareDeviceKey": 6,
                "MinValue": 0.0000,
                "MaxValue": 20.0000,
                "DefaultDelayedValue": 0,
                "DefaultOpenValue": 0.00,
                "DefaultOpenValueOperate": 1,
                "DefaultMinDuration": 0,
                "DefaultMinComplete": 0,
                "DeviceUnit": "℃",
                "DeviceUnitDesc": "默认阈值(温度)",
                "DeviceNumberType": 1,
                "DeviceNumberPrecision": "0.0",
                "DeviceNormalValue": 0
            }],
            "IOTSceneWorkTimes": [{
                "StartTime": "00:00:00",
                "EndTime": "23:59:59"
            }]
        },
        "IOTClassifyNum": 1,
        "IOTDeviceTypeId": "5f7c8f60-3bf0-4704-a2fd-b1a20b0f6f9e",
        "IOTSceneName": "药店阴凉区温湿度传感器",
        "IOTSceneMonitorName": "药店阴凉区温湿度-实时监测",
        "IOTSceneLegalRule": "药品管理法要求阴凉区温湿度在正常范围",
        "IOTSceneWarningContent": "#默认阈值(温度)#药店阴凉区温湿度出现异常，当前温度：{NowValue}℃，|#默认阈值(湿度)#当前湿度：{NowValue}%，请立即处理！",
        "DeviceModels": null,
        "PersonWarningSets": null,
        "PersonWarningContent": null
    }, {
        "IOTSceneId": "be72dd93-6214-4f58-9e76-7eeb5f8938eb",
        "HardWareDeviceKey": 8,
        "IOTSceneBind": {
            "IOTSceneThresholds": [{
                "HardWareDeviceKey": 6,
                "MinValue": 10.0000,
                "MaxValue": 30.0000,
                "DefaultDelayedValue": 0,
                "DefaultOpenValue": 0.00,
                "DefaultOpenValueOperate": 1,
                "DefaultMinDuration": 0,
                "DefaultMinComplete": 0,
                "DeviceUnit": "℃",
                "DeviceUnitDesc": "默认阈值(温度)",
                "DeviceNumberType": 1,
                "DeviceNumberPrecision": "0.0",
                "DeviceNormalValue": 0
            }, {
                "HardWareDeviceKey": 7,
                "MinValue": 35.0000,
                "MaxValue": 75.0000,
                "DefaultDelayedValue": 0,
                "DefaultOpenValue": 0.00,
                "DefaultOpenValueOperate": 1,
                "DefaultMinDuration": 0,
                "DefaultMinComplete": 0,
                "DeviceUnit": "%",
                "DeviceUnitDesc": "默认阈值(湿度)",
                "DeviceNumberType": 1,
                "DeviceNumberPrecision": "0.0",
                "DeviceNormalValue": 0
            }],
            "IOTSceneWorkTimes": [{
                "StartTime": "00:00:00",
                "EndTime": "23:59:59"
            }]
        },
        "IOTClassifyNum": 1,
        "IOTDeviceTypeId": "5f7c8f60-3bf0-4704-a2fd-b1a20b0f6f9e",
        "IOTSceneName": "药店大堂温湿度传感器",
        "IOTSceneMonitorName": "药店大堂温湿度-实时监测",
        "IOTSceneLegalRule": "药品管理法要求营业区温湿度在正常范围",
        "IOTSceneWarningContent": "#默认阈值(温度)#药店大堂温湿度出现异常，当前温度：{NowValue}℃，|#默认阈值(湿度)#当前湿度：{NowValue}%，请立即处理！",
        "DeviceModels": null,
        "PersonWarningSets": null,
        "PersonWarningContent": null
    }, {
        "IOTSceneId": "56d0fd3b-dae7-48f1-9037-d5a53e400998",
        "HardWareDeviceKey": 33,
        "IOTSceneBind": {
            "IOTSceneThresholds": [{
                "HardWareDeviceKey": 33,
                "MinValue": 0.0000,
                "MaxValue": 0.0000,
                "DefaultDelayedValue": 0,
                "DefaultOpenValue": 20.00,
                "DefaultOpenValueOperate": 1,
                "DefaultMinDuration": 20,
                "DefaultMinComplete": 1,
                "DeviceUnit": "mg/m3",
                "DeviceUnitDesc": "默认开启值(臭氧强度)",
                "DeviceNumberType": 1,
                "DeviceNumberPrecision": "0.0",
                "DeviceNormalValue": 0
            }],
            "IOTSceneWorkTimes": [{
                "StartTime": "00:00:00",
                "EndTime": "23:59:59"
            }]
        },
        "IOTClassifyNum": 3,
        "IOTDeviceTypeId": "834a4bf6-55d1-4073-b6b4-8f0aac1e7b5a",
        "IOTSceneName": "消毒柜臭氧浓度传感器",
        "IOTSceneMonitorName": "消毒柜臭氧消毒任务监测",
        "IOTSceneLegalRule": "食品生产法要求每日需对设施设备进行消毒",
        "IOTSceneWarningContent": "消毒柜今日还未进行臭氧消毒，请立即处理！",
        "DeviceModels": null,
        "PersonWarningSets": null,
        "PersonWarningContent": null
    }],
    "Message": "操作成功",
    "IsSuccess": true,
    "Code": "1",
    "Data": null,
    "Detail": null
}
